certbot_dns_rcode0.py
certbot_dns_rcode0-0.0.0.1.dist-info/DESCRIPTION.rst
certbot_dns_rcode0-0.0.0.1.dist-info/METADATA
certbot_dns_rcode0-0.0.0.1.dist-info/RECORD
certbot_dns_rcode0-0.0.0.1.dist-info/WHEEL
certbot_dns_rcode0-0.0.0.1.dist-info/entry_points.txt
certbot_dns_rcode0-0.0.0.1.dist-info/metadata.json
certbot_dns_rcode0-0.0.0.1.dist-info/top_level.txt
