Metadata-Version: 2.0
Name: certbot-dns-rcode0
Version: 0.0.0.1
Summary: RcodeZero DNS Authenticator plugin for Certbot
Home-page: https://github.com/nic-at/certbot-dns-rcode0
Author: Michael Braunoeder
Author-email: mib@nic.at
License: Apache License 2.0
Platform: UNKNOWN
Classifier: Development Status :: 3 - Alpha
Classifier: Environment :: Plugins
Classifier: Intended Audience :: System Administrators
Classifier: License :: OSI Approved :: Apache Software License
Classifier: Operating System :: POSIX :: Linux
Classifier: Programming Language :: Python
Classifier: Programming Language :: Python :: 2
Classifier: Programming Language :: Python :: 2.7
Classifier: Programming Language :: Python :: 3
Classifier: Programming Language :: Python :: 3.4
Classifier: Programming Language :: Python :: 3.5
Classifier: Programming Language :: Python :: 3.6
Classifier: Programming Language :: Python :: 3.7
Classifier: Topic :: Internet :: WWW/HTTP
Classifier: Topic :: Security
Classifier: Topic :: System :: Installation/Setup
Classifier: Topic :: System :: Networking
Classifier: Topic :: System :: Systems Administration
Classifier: Topic :: Utilities
Requires-Python: >=2.7, !=3.0.*, !=3.1.*, !=3.2.*, !=3.3.*
Requires-Dist: acme (>=0.31.0)
Requires-Dist: certbot (>=0.31.0)
Requires-Dist: dns-lexicon (>=3.3.11)
Requires-Dist: zope.interface
